LICENSE
MANIFEST.in
README.rst
setup.py
django_suit2.egg-info/PKG-INFO
django_suit2.egg-info/SOURCES.txt
django_suit2.egg-info/dependency_links.txt
django_suit2.egg-info/not-zip-safe
django_suit2.egg-info/top_level.txt
docs/Makefile
docs/conf.py
docs/configure.rst
docs/contribute.rst
docs/index.rst
docs/install.rst
suit/__init__.py
suit/admin.py
suit/admin_filters.py
suit/apps.py
suit/compat.py
suit/config.py
suit/menu.py
suit/sortables.py
suit/template.py
suit/widgets.py
suit/static/admin/css/changelists.css
suit/static/admin/css/dashboard.css
suit/static/admin/css/forms.css
suit/static/admin/css/login.css
suit/static/suit/css/font-awesome.min.css
suit/static/suit/css/suit.css
suit/static/suit/fonts/FontAwesome.otf
suit/static/suit/fonts/fontawesome-webfont.eot
suit/static/suit/fonts/fontawesome-webfont.svg
suit/static/suit/fonts/fontawesome-webfont.ttf
suit/static/suit/fonts/fontawesome-webfont.woff
suit/static/suit/fonts/fontawesome-webfont.woff2
suit/static/suit/js/autosize.min.js
suit/static/suit/js/suit.js
suit/static/suit/js/suit.sortables.js
suit/templates/admin/base.html
suit/templates/admin/base_site.html
suit/templates/admin/change_form.html
suit/templates/admin/change_list.html
suit/templates/admin/change_list_results.html
suit/templates/admin/filter_horizontal.html
suit/templates/admin/login.html
suit/templates/admin/auth/user/add_form.html
suit/templates/admin/includes/fieldset.html
suit/templates/registration/password_change_form.html
suit/templates/suit/change_form_includes.html
suit/templates/suit/menu.html
suit/templates/suit/menu_item.html
suit/templates/suit/search_form.html
suit/templatetags/__init__.py
suit/templatetags/suit_forms.py
suit/templatetags/suit_list.py
suit/templatetags/suit_menu.py
suit/templatetags/suit_tags.py