Metadata-Version: 1.1
Name: django-suit2
Version: 2.0a1
Summary: Modern theme for Django admin interface. (Making the latest updates available on Pypi)
Home-page: http://djangosuit.com
Author: Kaspars Sprogis (darklow)
Author-email: info@djangosuit.com
License: UNKNOWN
Platform: UNKNOWN
Classifier: Development Status :: 5 - Production/Stable
Classifier: Framework :: Django
Classifier: License :: Free for non-commercial use
Classifier: Intended Audience :: Developers
Classifier: Intended Audience :: System Administrators
Classifier: Operating System :: OS Independent
Classifier: Programming Language :: Python
Classifier: Programming Language :: Python :: 2.7
Classifier: Programming Language :: Python :: 3.4
Classifier: Programming Language :: Python :: 3.5
Classifier: Programming Language :: Python :: 3.6
Classifier: Environment :: Web Environment
Classifier: Topic :: Software Development
Classifier: Topic :: Software Development :: User Interfaces
